spomso/__init__.py
spomso/cores/__init__.py
spomso/cores/combine.py
spomso/cores/geom.py
spomso/cores/geom_2d.py
spomso/cores/geom_3d.py
spomso/cores/geom_vector.py
spomso/cores/geom_vector_special.py
spomso/cores/helper_functions.py
spomso/cores/modifications.py
spomso/cores/post_processing.py
spomso/cores/sdf_2D.py
spomso/cores/sdf_3D.py
spomso/cores/transformations.py
spomso/cores/triangulation_functions.py
spomso/cores/vector_functions.py
spomso/cores/vector_functions_special.py
spomso/cores/vector_modification_functions.py
spomso/jax_cores/__init__.py
spomso/jax_cores/combine_jax.py
spomso/jax_cores/helper_functions.py
spomso/jax_cores/modifications_jax.py
spomso/jax_cores/post_processing_jax.py
spomso/jax_cores/sdf_2D_jax.py
spomso/jax_cores/sdf_3D_jax.py
spomso/jax_cores/transformations_jax.py
spomso-1.3.0.dist-info/licenses/LICENSE
spomso-1.3.0.dist-info/licenses/LICENSE_NOTICE
spomso-1.3.0.dist-info/METADATA
spomso-1.3.0.dist-info/WHEEL
spomso-1.3.0.dist-info/top_level.txt
spomso-1.3.0.dist-info/RECORD
